kgdata_core-4.0.2.dist-info/METADATA
kgdata_core-4.0.2.dist-info/WHEEL
kgdata_core-4.0.2.dist-info/licenses/LICENSE
kgdata_core/__init__.py
kgdata_core/__init__.pyi
kgdata_core/base.pyi
kgdata_core/kgdata_core.cpython-311-x86_64-linux-gnu.so
kgdata_core/models.pyi
kgdata_core/py.typed
kgdata_core-4.0.2.dist-info/RECORD
