Metadata-Version: 2.4
Name: kgdata_core
Version: 4.0.2
Classifier: Programming Language :: Rust
Classifier: Programming Language :: Python :: Implementation :: CPython
Requires-Dist: python-dotenv>=0.19.0,<0.20.0 ; extra == 'dev'
Requires-Dist: pytest>=8.3.2,<9.0.0 ; extra == 'dev'
Requires-Dist: kgdata-core[dev] ; extra == 'all'
Provides-Extra: dev
Provides-Extra: all
License-File: LICENSE
License-File: LICENSE
Summary: Library to process dumps of knowledge graphs (Wikipedia, DBpedia, Wikidata)
Home-Page: https://github.com/binh-vu/kgdata
Author-email: Binh Vu <binh@toan2.com>
Requires-Python: >=3.10
Project-URL: homepage, https://github.com/binh-vu/kgdata
Project-URL: repository, https://github.com/binh-vu/kgdata
